README.txt
bootstrap.py
setup.cfg
setup.py
test-plone-3.3.x.cfg
test-plone-4.0.x.cfg
test-plone-4.1.x.cfg
docs/HISTORY.txt
docs/INSTALL.txt
docs/LICENSE.GPL
docs/LICENSE.txt
sc/__init__.py
sc.contentrules.movebyattribute.egg-info/PKG-INFO
sc.contentrules.movebyattribute.egg-info/SOURCES.txt
sc.contentrules.movebyattribute.egg-info/dependency_links.txt
sc.contentrules.movebyattribute.egg-info/entry_points.txt
sc.contentrules.movebyattribute.egg-info/namespace_packages.txt
sc.contentrules.movebyattribute.egg-info/not-zip-safe
sc.contentrules.movebyattribute.egg-info/requires.txt
sc.contentrules.movebyattribute.egg-info/top_level.txt
sc/contentrules/__init__.py
sc/contentrules/movebyattribute/README.txt
sc/contentrules/movebyattribute/__init__.py
sc/contentrules/movebyattribute/action.py
sc/contentrules/movebyattribute/configure.zcml
sc/contentrules/movebyattribute/interfaces.py
sc/contentrules/movebyattribute/version.txt
sc/contentrules/movebyattribute/vocabulary.py
sc/contentrules/movebyattribute/locales/manual.pot
sc/contentrules/movebyattribute/locales/rebuildAll.sh
sc/contentrules/movebyattribute/locales/sc.contentrules.movebyattribute.pot
sc/contentrules/movebyattribute/locales/pt_BR/LC_MESSAGES/sc.contentrules.movebyattribute.po
sc/contentrules/movebyattribute/tests/__init__.py
sc/contentrules/movebyattribute/tests/base.py
sc/contentrules/movebyattribute/tests/test_action_movebyattribute.py